doug-cli
setup.py
libdoug/__init__.py
libdoug/conflict.py
libdoug/conflict_resolution.py
libdoug/decorators.py
libdoug/dependency_walker.py
libdoug/docker_api.py
libdoug/graph.py
libdoug/history.py
libdoug/http.py
libdoug/optimistic_solver.py
libdoug/registry.py
libdoug/token.py
libdoug/utils.py
libdoug/values.py
libdoug/vr_solver.py
libdoug.egg-info/PKG-INFO
libdoug.egg-info/SOURCES.txt
libdoug.egg-info/dependency_links.txt
libdoug.egg-info/requires.txt
libdoug.egg-info/top_level.txt
libdoug/api/__init__.py
libdoug/api/flags.py
libdoug/api/remote_base.py
libdoug/api/remote_docker.py
libdoug/api/remote_hub.py
libdoug/api/remote_registry.py