Metadata-Version: 1.0
Name: libdoug
Version: 0.4
Summary: High level library around Docker Daemon, Registry and Hub
Home-page: https://github.com/shaded-enmity/docker-doug
Author: Pavel Odvody
Author-email: podvody@redhat.com
License: GNU/GPLv2
Keywords: docker cli updates
Platform: UNKNOWN
